inarpa.py
setup.py
inarpa.egg-info/PKG-INFO
inarpa.egg-info/SOURCES.txt
inarpa.egg-info/dependency_links.txt
inarpa.egg-info/top_level.txt
inarpa.egg-info/zip-safe